Workbook
Name Aporte: APP!$D$18
Name Dividendos_Mensais: APP!$D$22
Name Patrimonio_Acumulado: APP!$D$21
Name Período_aplicação: APP!$D$19
Name Rendimento_Carteira: APP!$D$14
Name Salario: APP!$D$13

Sheet APP
B12: CONFIGURAÇÕES
B13: Salario | D13: 5000
B14: Rendimento Carteira | D14: 0.008
B15: Sugestão Investimento (30%) | D15: =D13*30% -> 1500
B17: INVESTIMENTO MENSAL
B18: Quanto investir por mês? | D18: 500
B19: Por quantos anos? | D19: 10
B20: Taxa de rendimento mensal? | D20: =Rendimento_Carteira -> 0.008
A21: 2 | B21: Patrimônio acumulado? | D21: =FV(Rendimento_Carteira,Período_aplicação*12,Aporte*-1) -> 100108.73
A22: 5 | B22: Dividendos mensais? | D22: =Patrimonio_Acumulado*Rendimento_Carteira -> 800.86988
A23: 10
B24: CENÁRIOS | D24: DIVIDENDOS
A25: 2 | B25: Quanto em 02 anos? | C25: =FV($D$20,$A25*12,$D$18*-1) -> 13171.578 | D25: =C25*Rendimento_Carteira -> 105.37262
A26: 5 | B26: Quanto em 05 anos? | C26: =FV($D$20,$A26*12,$D$18*-1) -> 38311.933 | D26: =C26*Rendimento_Carteira -> 306.49547
A27: 10 | B27: Quanto em 10 anos? | C27: =FV($D$20,$A27*12,$D$18*-1) -> 100108.73 | D27: =C27*Rendimento_Carteira -> 800.86988
A28: 20 | B28: Quanto em 20 anos? | C28: =FV($D$20,$A28*12,$D$18*-1) -> 360565.61 | D28: =C28*Rendimento_Carteira -> 2884.5249
A29: 30 | B29: Quanto em 30 anos? | C29: =FV($D$20,$A29*12,$D$18*-1) -> 1038206.6 | D29: =C29*Rendimento_Carteira -> 8305.6529
B32: PERFIL | C32: CONSERVADOR
B33: VALOR INVESTIDO POR MÊS | C33: =Aporte -> 500
B35: TIPO DE FII | C35: Percentual sugerido | D35: Valores
B36: PAPEL | C36: =VLOOKUP($C$32&"-"&B36,Chave_Composta!$A:$D,4,FALSE) -> 0.3 | D36: =C36*$C$33 -> 150
B37: TIJOLO | C37: =VLOOKUP($C$32&"-"&B37,Chave_Composta!$A:$D,4,FALSE) -> 0.5 | D37: =C37*$C$33 -> 250
B38: HIBRIDOS | C38: =VLOOKUP($C$32&"-"&B38,Chave_Composta!$A:$D,4,FALSE) -> 0.1 | D38: =C38*$C$33 -> 50
B39: FOFs | C39: =VLOOKUP($C$32&"-"&B39,Chave_Composta!$A:$D,4,FALSE) -> 0.1 | D39: =C39*$C$33 -> 50
B40: DESENVOLVIMENTO | C40: =VLOOKUP($C$32&"-"&B40,Chave_Composta!$A:$D,4,FALSE) -> 0 | D40: =C40*$C$33 -> 0
B41: HOTELARIA | C41: =VLOOKUP($C$32&"-"&B41,Chave_Composta!$A:$D,4,FALSE) -> 0 | D41: =C41*$C$33 -> 0
D42: =SUM(D36:D41) -> 500

Sheet Chave_Composta
A1: CHAVE COMPOSTA
A2: CHAVE | B2: PERFIL | C2: TIPO FII | D2: %
A3: =B3&"-"&C3 -> CONSERVADOR-PAPEL | B3: CONSERVADOR | C3: PAPEL | D3: 0.3
A4: =B4&"-"&C4 -> CONSERVADOR-TIJOLO | B4: CONSERVADOR | C4: TIJOLO | D4: 0.5
A5: =B5&"-"&C5 -> CONSERVADOR-HIBRIDOS | B5: CONSERVADOR | C5: HIBRIDOS | D5: 0.1
A6: =B6&"-"&C6 -> CONSERVADOR-FOFs | B6: CONSERVADOR | C6: FOFs | D6: 0.1
A7: =B7&"-"&C7 -> CONSERVADOR-DESENVOLVIMENTO | B7: CONSERVADOR | C7: DESENVOLVIMENTO | D7: 0
A8: =B8&"-"&C8 -> CONSERVADOR-HOTELARIA | B8: CONSERVADOR | C8: HOTELARIA | D8: 0
A9: =B9&"-"&C9 -> MODERADO-PAPEL | B9: MODERADO | C9: PAPEL | D9: 0.32
A10: =B10&"-"&C10 -> MODERADO-TIJOLO | B10: MODERADO | C10: TIJOLO | D10: 0.35
A11: =B11&"-"&C11 -> MODERADO-HIBRIDOS | B11: MODERADO | C11: HIBRIDOS | D11: 0.08
A12: =B12&"-"&C12 -> MODERADO-FOFs | B12: MODERADO | C12: FOFs | D12: 0.1
A13: =B13&"-"&C13 -> MODERADO-DESENVOLVIMENTO | B13: MODERADO | C13: DESENVOLVIMENTO | D13: 0.1
A14: =B14&"-"&C14 -> MODERADO-HOTELARIA | B14: MODERADO | C14: HOTELARIA | D14: 0.1
... A20: =B20&"-"&C20 -> AGRESSIVO-HOTELARIA | B20: AGRESSIVO | C20: HOTELARIA | D20: 0.1
